COde_verilog_tham_khao/Counter_dolphin/counter.v
module counter(clk,reset_n,load_en,count_dec,count_inc,count_to,flag_max,flag_min);
input clk;
input reset_n,count_dec, count_inc, load_en;
input [3:0]count_to;
output flag_max,flag_min;
reg flag_max,flag_min;
reg [3:0]counter, count_max;
reg [2:0] state, next_state; 
parameter S0 = 4'd0; // ko tang giam
parameter S1 = 4'd1;// tang
parameter S2 = 4'd2;// giam
parameter S3 = 4'd3;// max
parameter S4 = 4'd4;// min

always @( posedge clk or posedge reset_n ) begin 
    if( reset_n) begin 
        counter <= 4'd0;
        flag_max<=4'd0;
        flag_min<=4'd0;
    end
    else state <= next_state;
end

always @( state or count_dec or count_inc ) begin 
    case ( state )
            S0: begin 
                if( count_inc == 1'd1 & count_dec == 1'd0 ) next_state = S1;
                else begin 
                    if( count_dec == 1'd1 & count_inc == 1'd0 ) next_state = S2;
                else next_state = S0;
                end
            end
            S1: begin 
                next_state = (counter == count_max)? S3 : (( counter == 4'b0000)? S4: S0); 
                if( count_inc == 1'd1 & count_dec == 1'd0 ) next_state = S1;
                else begin 
                    if( count_dec == 1'd1 & count_inc == 1'd0 ) next_state = S2;
                else next_state = S0;
                end
            end
            S2: begin 
                next_state = (counter == count_max)? S3 : (( counter == 4'b0000)? S4: S0); 
                if( count_inc == 1'd1 & count_dec == 1'd0 ) next_state = S1;
                else begin 
                    if( count_dec == 1'd1 & count_inc == 1'd0 ) next_state = S2;
                else next_state = S0;
                end
            end
            S3: begin
                if( count_inc == 1'd1 & count_dec == 1'd0 ) next_state = S1;
                else begin 
                    if( count_dec == 1'd1 & count_inc == 1'd0 ) next_state = S2;
                else next_state = S0;
                end
            end
            S4:begin if( count_inc == 1'd1 & count_dec == 1'd0 ) next_state = S1;
                else begin 
                    if( count_dec == 1'd1 & count_inc == 1'd0 ) next_state = S2;
                else next_state = S0;
                end
            end
    endcase 
end
always @( state or count_dec or count_inc ) begin 
    state = S0;
case(state) 
        S0: ;
        S1: counter = counter + 1;
        S2: counter = counter - 1;
        S3: begin 
            counter = 4'b0000; flag_max = 1'b1;
        end
        S4: begin 
            counter = 4'b0000; flag_min = 1'b1;
        end

endcase
end
always @(posedge clk) begin 
        if(load_en) count_max <= count_to;
end
endmodule

COde_verilog_tham_khao/Counter_dolphin/testbench.v
module testbench;
reg clk,load_en, reset_n,count_dec,count_inc;
reg [3:0] count_to;
wire flag_max,flag_min;

counter ct( clk,reset_n,load_en,count_dec,count_inc,count_to,flag_max,flag_min );
initial begin
    $dumpfile( " counter.vcd");
    $dumpvars(0,testbench);
end
initial begin 
    clk = 1'b0;
    reset_n = 1'b1;
    count_to = 4'b1111;
    count_dec = 1'b0;
    count_inc = 1'b0;
    #5 load_en = 1'b1;
    #5 load_en = 1'b0;
    reset_n = 1'b0;
     count_dec = 1'b0;
    count_inc = 1'b1;
end
always #5 clk = ~clk;
initial #200 $finish;
endmodule

COde_verilog_tham_khao/Counter_dolphin/ counter.vcd
$date
	Wed Aug 23 14:21:06 2023
$end
$version
	Icarus Verilog
$end
$timescale
	1s
$end
$scope module testbench $end
$var wire 1 ! flag_min $end
$var wire 1 " flag_max $end
$var reg 1 # clk $end
$var reg 1 $ count_dec $end
$var reg 1 % count_inc $end
$var reg 4 & count_to [3:0] $end
$var reg 1 ' load_en $end
$var reg 1 ( reset_n $end
$scope module ct $end
$var wire 1 # clk $end
$var wire 1 $ count_dec $end
$var wire 1 % count_inc $end
$var wire 4 ) count_to [3:0] $end
$var wire 1 ' load_en $end
$var wire 1 ( reset_n $end
$var reg 4 * count_max [3:0] $end
$var reg 4 + counter [3:0] $end
$var reg 1 " flag_max $end
$var reg 1 ! flag_min $end
$var reg 3 , next_state [2:0] $end
$var reg 3 - state [2:0] $end
$upscope $end
$upscope $end
$enddefinitions $end
#0
$dumpvars
b0 -
b0 ,
b0 +
bx *
b1111 )
1(
x'
b1111 &
0%
0$
0#
0"
0!
$end
#5
b1111 *
1#
1'
#10
b1 ,
0#
1%
0(
0'
#15
b0 -
1#
#20
0#
#25
b1 ,
b0 -
1#
#30
0#
#35
b1 ,
b0 -
1#
#40
0#
#45
b1 ,
b0 -
1#
#50
0#
#55
b1 ,
b0 -
1#
#60
0#
#65
b1 ,
b0 -
1#
#70
0#
#75
b1 ,
b0 -
1#
#80
0#
#85
b1 ,
b0 -
1#
#90
0#
#95
b1 ,
b0 -
1#
#100
0#
#105
b1 ,
b0 -
1#
#110
0#
#115
b1 ,
b0 -
1#
#120
0#
#125
b1 ,
b0 -
1#
#130
0#
#135
b1 ,
b0 -
1#
#140
0#
#145
b1 ,
b0 -
1#
#150
0#
#155
b1 ,
b0 -
1#
#160
0#
#165
b1 ,
b0 -
1#
#170
0#
#175
b1 ,
b0 -
1#
#180
0#
#185
b1 ,
b0 -
1#
#190
0#
#195
b1 ,
b0 -
1#
